{"timestamp": "2025-08-13T15:25:21.579853", "signal_id": "SIG1755098721", "pair": "ADA/USD", "direction": "\ud83d\udcc9 SELL", "accuracy": 94.2, "confidence": 93.6, "expiry_time": "15:27:21", "pair_type": "Regular"}
{"timestamp": "2025-08-13T15:25:51.580729", "signal_id": "SIG1755098751", "pair": "GBP/USD", "direction": "\ud83d\udcc9 SELL", "accuracy": 88.8, "confidence": 82.6, "expiry_time": "15:28:51", "pair_type": "Regular"}
{"timestamp": "2025-08-13T15:26:21.581351", "signal_id": "SIG1755098781", "pair": "EUR/HUF", "direction": "\ud83d\udcc9 SELL", "accuracy": 96.3, "confidence": 93.4, "expiry_time": "15:28:21", "pair_type": "Regular"}
{"timestamp": "2025-08-13T15:26:51.582092", "signal_id": "SIG1755098811", "pair": "SPX500", "direction": "\ud83d\udcc8 BUY", "accuracy": 92.8, "confidence": 94.3, "expiry_time": "15:28:51", "pair_type": "Regular"}
